pvv_mcp_server/__init__.py
pvv_mcp_server/main.py
pvv_mcp_server/mod_avatar_manager.py
pvv_mcp_server/mod_emotion.py
pvv_mcp_server/mod_service.py
pvv_mcp_server/mod_speak.py
pvv_mcp_server/mod_speaker_info.py
pvv_mcp_server/mod_speakers.py
pvv_mcp_server/avatar/mod_avatar.py
pvv_mcp_server/avatar/mod_avatar_dialog.py
pvv_mcp_server/avatar/mod_avatar_part.py
pvv_mcp_server/avatar/mod_load_image.py
pvv_mcp_server/avatar/mod_right_click_context_menu.py
pvv_mcp_server/avatar/mod_update_frame.py
pvv_mcp_server/avatar/mod_update_position.py
pvv_mcp_server-0.6.0.dist-info/licenses/LICENSE
pvv_mcp_server-0.6.0.dist-info/METADATA
pvv_mcp_server-0.6.0.dist-info/WHEEL
pvv_mcp_server-0.6.0.dist-info/entry_points.txt
pvv_mcp_server-0.6.0.dist-info/top_level.txt
pvv_mcp_server-0.6.0.dist-info/RECORD
