Metadata-Version: 2.4
Name: pvv-mcp-server
Version: 0.6.0
Summary: MCP server for VOICEVOX text-to-speech synthesis
Author-email: Aska Lanclaude <crypto.tuber.magika@gmail.com>
License-Expression: Apache-2.0
Project-URL: Homepage, https://github.com/lambda-tuber/pvv-mcp-server
Keywords: VOICEVOX,MCP,FastMCP,TTS,AI,voice synthesis
Requires-Python: >=3.11
License-File: LICENSE
Requires-Dist: mcp>=0.1.0
Requires-Dist: requests>=2.31.0
Requires-Dist: sounddevice>=0.4.6
Requires-Dist: soundfile>=0.13.1
Requires-Dist: numpy>=1.24.0
Requires-Dist: PySide6>=6.9.3
Requires-Dist: pygetwindow>=0.0.9
Requires-Dist: pyyaml>=6.0.3
Requires-Dist: Pillow>=11.3.0
Provides-Extra: dev
Requires-Dist: pytest>=8.0.0; extra == "dev"
Requires-Dist: pytest-asyncio>=0.23.0; extra == "dev"
Dynamic: license-file
